gogo_crawler/__init__.py
gogo_crawler/main.py
gogo_crawler/downloader/__init__.py
gogo_crawler/downloader/downloader.py
gogo_crawler/downloader/gogo_download.py
gogo_crawler/downloader/movies_dowload.py
gogo_crawler/exception/__init__.py
gogo_crawler/exception/exception.py
gogo_crawler/extractor/__init__.py
gogo_crawler/extractor/htmlextractor.py
gogo_crawler/series/__init__.py
gogo_crawler/series/gogo_series.py
gogo_crawler-0.1.12.dist-info/LICENSE
gogo_crawler-0.1.12.dist-info/METADATA
gogo_crawler-0.1.12.dist-info/WHEEL
gogo_crawler-0.1.12.dist-info/top_level.txt
gogo_crawler-0.1.12.dist-info/RECORD
