Metadata-Version: 2.1
Name: gogo-crawler
Version: 0.1.12
Summary: A small example package
Author: Juran Kirihara
Author-email: kirihara.juran@gmail.com
Classifier: Programming Language :: Python :: 3
Classifier: License :: OSI Approved :: MIT License
Classifier: Operating System :: OS Independent
Requires-Python: >=3.9
License-File: LICENSE
Requires-Dist: requests
Requires-Dist: bs4
Requires-Dist: requests-html
Requires-Dist: pySmartDL
